x86.cp36-win_amd64.pyd
tdasm/__init__.py
tdasm/avx2_i.py
tdasm/avx_512.py
tdasm/avx_i.py
tdasm/code.py
tdasm/cpuinfo.py
tdasm/encoder.py
tdasm/fma_i.py
tdasm/fpu_i.py
tdasm/general_i.py
tdasm/holders.py
tdasm/insts.py
tdasm/lex.py
tdasm/mmx_i.py
tdasm/parser.py
tdasm/regs.py
tdasm/runtime.py
tdasm/sse2_i.py
tdasm/sse3_i.py
tdasm/sse41_i.py
tdasm/sse42_i.py
tdasm/sse_i.py
tdasm/ssse3_i.py
tdasm/tdasm.py
tdasm-0.6.0.dist-info/DESCRIPTION.rst
tdasm-0.6.0.dist-info/METADATA
tdasm-0.6.0.dist-info/RECORD
tdasm-0.6.0.dist-info/WHEEL
tdasm-0.6.0.dist-info/metadata.json
tdasm-0.6.0.dist-info/top_level.txt
