Metadata-Version: 2.0
Name: tdasm
Version: 0.6.0
Summary: Tdasm is dynamic X86 assembler for python
Home-page: https://bitbucket.org/Tahir007/tdasm
Author: Mario Vidov
Author-email: mvidov@yahoo.com
License: MIT
Keywords: assembler simd SSE AVX FMA AVX-512
Platform: UNKNOWN
Classifier: Intended Audience :: Developers
Classifier: Programming Language :: Assembly
Classifier: Topic :: Software Development :: Assemblers
Classifier: License :: OSI Approved :: MIT License
Classifier: Programming Language :: Python :: 3.5
Classifier: Programming Language :: Python :: 3.6
